mlcb/__init__.py
mlcb/base_classes/BaseTunableModel.py
mlcb/base_classes/__init__.py
mlcb/base_classes/helpers/MLFlowLogger.py
mlcb/base_classes/helpers/MetricsHelper.py
mlcb/base_classes/helpers/PlotHelper.py
mlcb/base_classes/helpers/__init__.py
mlcb/base_classes/pytorch/EarlyStopping.py
mlcb/base_classes/pytorch/NetworkxGraphDataset.py
mlcb/base_classes/pytorch/PytorchGeometricTunable.py
mlcb/base_classes/pytorch/PytorchTabularTunable.py
mlcb/base_classes/pytorch/PytorchTunable.py
mlcb/base_classes/pytorch/__init__.py
mlcb/base_classes/sklearn/SklearnTunable.py
mlcb/base_classes/sklearn/__init__.py
mlcb/base_classes/tensorflow/TensorflowTunable.py
mlcb/base_classes/tensorflow/__init__.py
mlcb/models/__init__.py
mlcb/models/graph/__init__.py
mlcb/models/graph/pytorch/AppnpNetworkTunable.py
mlcb/models/graph/pytorch/GatNetworkTunable.py
mlcb/models/graph/pytorch/GcnGatNetworkTunable.py
mlcb/models/graph/pytorch/GcnNetworkTunable.py
mlcb/models/graph/pytorch/GcnSageNetworkTunable.py
mlcb/models/graph/pytorch/GinNetworkTunable.py
mlcb/models/graph/pytorch/LeNetworkTunable.py
mlcb/models/graph/pytorch/SageNetworkTunable.py
mlcb/models/graph/pytorch/SgNetworkTunable.py
mlcb/models/graph/pytorch/TagNetworkTunable.py
mlcb/models/graph/pytorch/TransformerNetworkTunable.py
mlcb/models/graph/pytorch/__init__.py
mlcb/models/tabular/__init__.py
mlcb/models/tabular/pytorch/PytorchDenseNetworkTunable.py
mlcb/models/tabular/pytorch/PytorchFeedForwardNetworkTunable.py
mlcb/models/tabular/pytorch/PytorchMixtureOfExpertsNetworkTunable.py
mlcb/models/tabular/pytorch/PytorchResNetNetworkTunable.py
mlcb/models/tabular/pytorch/PytorchSelfNormalizingNetworkTunable.py
mlcb/models/tabular/pytorch/PytorchTangentKernelNetworkTunable.py
mlcb/models/tabular/pytorch/PytorchWideDeepNetworkTunable.py
mlcb/models/tabular/pytorch/__init__.py
mlcb/models/tabular/pytorch_tabular/PyTorchTabularAutoIntNetworkTunable.py
mlcb-0.6.4.dist-info/LICENSE
mlcb-0.6.4.dist-info/METADATA
mlcb-0.6.4.dist-info/WHEEL
mlcb-0.6.4.dist-info/top_level.txt
mlcb-0.6.4.dist-info/RECORD
