Metadata-Version: 2.1
Name: mlcb
Version: 0.6.4
Home-page: https://github.com/mbry24/MLCB
Author: Michał Bryła
Author-email: michal.bryla@wat.edu.pl
Project-URL: Bug Tracker, https://github.com/mbry24/MLCB/issues
Classifier: Programming Language :: Python :: 3
Classifier: License :: OSI Approved :: MIT License
Classifier: Operating System :: OS Independent
Requires-Python: >=3.11
License-File: LICENSE
